simple_transformer/__init__.py
simple_transformer/decoder.py
simple_transformer/encoder.py
simple_transformer/self_attention.py
simple_transformer/transformer.py
simple_transformer/transformer_block.py
simple_transformer-0.0.1.dist-info/LICENSE
simple_transformer-0.0.1.dist-info/METADATA
simple_transformer-0.0.1.dist-info/WHEEL
simple_transformer-0.0.1.dist-info/top_level.txt
simple_transformer-0.0.1.dist-info/RECORD
