Metadata-Version: 2.2
Name: simple-transformer
Version: 0.0.1
Summary: A simple and modular implementation of the Transformer model in PyTorch
Home-page: https://github.com/nullHawk/simple-transformer
Author: Suryansh Shakya
Author-email: suryanshsinghshakya1@gmail.com
Classifier: Programming Language :: Python :: 3
Classifier: Programming Language :: Python :: 3.7
Classifier: License :: OSI Approved :: MIT License
Classifier: Operating System :: OS Independent
License-File: LICENSE
Requires-Dist: torch
Dynamic: author
Dynamic: author-email
Dynamic: classifier
Dynamic: description
Dynamic: description-content-type
Dynamic: home-page
Dynamic: requires-dist
Dynamic: summary
